fumedev/LICENSE
fumedev/README.md
fumedev/__init__.py
fumedev/env.py
fumedev/main.py
fumedev/my-languages.so
fumedev/package-lock.json
fumedev/package.json
fumedev/prompts.py
fumedev/requirements.txt
fumedev/setup.sh
fumedev/start.sh
fumedev/__pycache__/__init__.cpython-311.pyc
fumedev/__pycache__/env.cpython-311.pyc
fumedev/__pycache__/globals.cpython-311.pyc
fumedev/__pycache__/main.cpython-311.pyc
fumedev/__pycache__/prompts.cpython-311.pyc
fumedev/agents/__init__.py
fumedev/agents/agent.py
fumedev/agents/coderMinion.py
fumedev/agents/philosopher.py
fumedev/agents/taskMaster.py
fumedev/agents/__pycache__/__init__.cpython-311.pyc
fumedev/agents/__pycache__/agent.cpython-311.pyc
fumedev/agents/__pycache__/coderMinion.cpython-311.pyc
fumedev/agents/__pycache__/omniscient.cpython-311.pyc
fumedev/agents/__pycache__/philosopher.cpython-311.pyc
fumedev/agents/__pycache__/taskMaster.cpython-311.pyc
fumedev/agents/utils/__init__.py
fumedev/agents/utils/find_code_blocks.py
fumedev/agents/utils/__pycache__/__init__.cpython-311.pyc
fumedev/agents/utils/__pycache__/find_code_blocks.cpython-311.pyc
fumedev/auth/__init__.py
fumedev/auth/auth.py
fumedev/auth/keys.py
fumedev/auth/__pycache__/__init__.cpython-311.pyc
fumedev/auth/__pycache__/auth.cpython-311.pyc
fumedev/auth/__pycache__/keys.cpython-311.pyc
fumedev/coder/HISTORY.md
fumedev/coder/LICENSE.txt
fumedev/coder/MANIFEST.in
fumedev/coder/README.md
fumedev/coder/__init__.py
fumedev/coder/_config.yml
fumedev/coder/dev-requirements.in
fumedev/coder/dev-requirements.txt
fumedev/coder/pytest.ini
fumedev/coder/requirements.in
fumedev/coder/requirements.txt
fumedev/coder/setup.py
fumedev/coder/__pycache__/__init__.cpython-311.pyc
fumedev/coder/_layouts/default.html
fumedev/coder/assets/aider-square.jpg
fumedev/coder/assets/aider.jpg
fumedev/coder/assets/benchmarks-0125.svg
fumedev/coder/assets/benchmarks-1106.svg
fumedev/coder/assets/benchmarks-speed-1106.svg
fumedev/coder/assets/benchmarks-udiff.svg
fumedev-0.2.10.dist-info/LICENSE
fumedev-0.2.10.dist-info/METADATA
fumedev-0.2.10.dist-info/WHEEL
fumedev-0.2.10.dist-info/entry_points.txt
fumedev-0.2.10.dist-info/top_level.txt
fumedev-0.2.10.dist-info/RECORD
