Metadata-Version: 2.1
Name: fumedev
Version: 0.2.10
Summary: AI pair programmer
Author: Metehan Oz
Author-email: metehanozdev@gmail.com
Classifier: Programming Language :: Python :: 3
Classifier: Operating System :: OS Independent
Requires-Python: >=3.6
License-File: LICENSE
Requires-Dist: tiktoken >=0.5.2
Requires-Dist: gitpython >=3.1.40
Requires-Dist: python-dotenv >=1.0.1
Requires-Dist: unidiff >=0.7.5
Requires-Dist: chardet >=5.2.0
Requires-Dist: python-Levenshtein >=0.25.0
Requires-Dist: PyJWT >=2.8.0
Requires-Dist: networkx >=3.2.1
Requires-Dist: pylint >=3.0.3
Requires-Dist: astor >=0.8.1
Requires-Dist: beautifulsoup4 >=4.12.3
Requires-Dist: lxml >=5.1.0
Requires-Dist: setuptools >=69.0.2
Requires-Dist: faiss-cpu >=1.7.4
Requires-Dist: tree-sitter >=0.20.4
Requires-Dist: tree-sitter-languages >=1.8.0
Requires-Dist: inquirer >=3.2.3
Requires-Dist: rich >=13.7.0
Requires-Dist: prompt-toolkit >=3.0.41
Requires-Dist: supabase >=2.3.4
Requires-Dist: cryptography >=42.0.2
Requires-Dist: configargparse >=1.7
Requires-Dist: GitPython >=3.1.40
Requires-Dist: openai >=1.3.7
Requires-Dist: jsonschema >=4.20.0
Requires-Dist: numpy >=1.26.2
Requires-Dist: scipy >=1.11.4
Requires-Dist: backoff >=2.2.1
Requires-Dist: pathspec >=0.11.2
Requires-Dist: diskcache >=5.6.3
Requires-Dist: grep-ast >=0.2.4
Requires-Dist: packaging >=23.2
Requires-Dist: sounddevice >=0.4.6
Requires-Dist: soundfile >=0.12.1
Requires-Dist: PyYAML >=6.0.1
Requires-Dist: Pillow >=10.1.0
Requires-Dist: diff-match-patch
Requires-Dist: playwright >=1.41.2
Requires-Dist: pypandoc >=1.12
Requires-Dist: click >=8.1.7
Requires-Dist: textual
Requires-Dist: textual-dev
Requires-Dist: Flask
Requires-Dist: slackclient
Requires-Dist: slackeventsapi
Requires-Dist: slack-sdk
Requires-Dist: slack-bolt
Requires-Dist: pylspclient
Requires-Dist: cohere
Requires-Dist: pygithub
Requires-Dist: gitpython
Requires-Dist: python-gitlab
Requires-Dist: jedi
Requires-Dist: sentry-sdk
Requires-Dist: posthog
